odoo/addons/datetime_formatter/README.rst
odoo/addons/datetime_formatter/__init__.py
odoo/addons/datetime_formatter/__manifest__.py
odoo/addons/datetime_formatter/i18n/ar.po
odoo/addons/datetime_formatter/i18n/ca.po
odoo/addons/datetime_formatter/i18n/datetime_formatter.pot
odoo/addons/datetime_formatter/i18n/de.po
odoo/addons/datetime_formatter/i18n/es.po
odoo/addons/datetime_formatter/i18n/fr.po
odoo/addons/datetime_formatter/i18n/hr.po
odoo/addons/datetime_formatter/i18n/it.po
odoo/addons/datetime_formatter/i18n/nl_NL.po
odoo/addons/datetime_formatter/i18n/pt.po
odoo/addons/datetime_formatter/i18n/sl.po
odoo/addons/datetime_formatter/i18n/tr.po
odoo/addons/datetime_formatter/i18n/zh_CN.po
odoo/addons/datetime_formatter/models/__init__.py
odoo/addons/datetime_formatter/models/res_lang.py
odoo/addons/datetime_formatter/readme/CONTRIBUTORS.rst
odoo/addons/datetime_formatter/readme/DESCRIPTION.rst
odoo/addons/datetime_formatter/readme/USAGE.rst
odoo/addons/datetime_formatter/static/description/icon.png
odoo/addons/datetime_formatter/static/description/index.html
odoo/addons/datetime_formatter/tests/__init__.py
odoo/addons/datetime_formatter/tests/test_best_matcher.py
odoo/addons/datetime_formatter/tests/test_formatter.py
odoo14_addon_datetime_formatter-14.0.1.0.1.dev5.dist-info/METADATA
odoo14_addon_datetime_formatter-14.0.1.0.1.dev5.dist-info/WHEEL
odoo14_addon_datetime_formatter-14.0.1.0.1.dev5.dist-info/top_level.txt
odoo14_addon_datetime_formatter-14.0.1.0.1.dev5.dist-info/RECORD
