Metadata-Version: 2.1
Name: odoo14-addon-datetime_formatter
Version: 14.0.1.0.1.dev5
Summary: Helper functions to give correct format to date[time] fields
Home-page: https://github.com/OCA/server-tools
Author: Grupo ESOC Ingeniería de Servicios, Tecnativa, Odoo Community Association (OCA)
Author-email: support@odoo-community.org
License: AGPL-3
Classifier: Programming Language :: Python
Classifier: Framework :: Odoo
Classifier: Framework :: Odoo :: 14.0
Classifier: License :: OSI Approved :: GNU Affero General Public License v3
Requires-Python: >=3.6
Requires-Dist: odoo<14.1dev,>=14.0a
